netlink/keepass/__init__.py
netlink/keepass/cli.py
netlink/keepass/keepass.py
netlink/keepass/reader.py
netlink/keepass/util.py
netlink_keepass-0.6.3.dist-info/entry_points.txt
netlink_keepass-0.6.3.dist-info/WHEEL
netlink_keepass-0.6.3.dist-info/METADATA
netlink_keepass-0.6.3.dist-info/RECORD
