Metadata-Version: 2.1
Name: netlink-keepass
Version: 0.6.3
Summary: Tools to work with (Py)KeePass
Home-page: https://gitlab.com/netlink_python/netlink-keepass.git
Author: Bernhard Radermacher
Author-email: bernhard.radermacher@netlink-consulting.com
Requires-Python: >=3.8.1,<3.13
Classifier: Programming Language :: Python :: 3
Classifier: Programming Language :: Python :: 3.10
Classifier: Programming Language :: Python :: 3.9
Requires-Dist: click (>=8.1.7)
Requires-Dist: cryptography (>=42.0.1)
Requires-Dist: fastapi (>=0.109.0)
Requires-Dist: pykeepass (>=4.0.6)
Requires-Dist: uvicorn (>=0.27.0)
Project-URL: Repository, https://gitlab.com/netlink_python/netlink-keepass.git
